MANIFEST.in
README.md
setup.py
hcontainer/LICENSE
hcontainer/README.md
hcontainer/__init__.py
hcontainer/bean.py
hcontainer/base/ClassReflection.py
hcontainer/base/Container.py
hcontainer/base/Definition.py
hcontainer/base/__init__.py
hcontainer/utils/BeanUtil.py
hcontainer/utils/__init__.py
hehey_hcontainer.egg-info/PKG-INFO
hehey_hcontainer.egg-info/SOURCES.txt
hehey_hcontainer.egg-info/dependency_links.txt
hehey_hcontainer.egg-info/top_level.txt