Metadata-Version: 2.1
Name: hehey-hcontainer
Version: 1.0.0
Summary: hehey-hcontainer 是一个python di 容器,提供依赖注入等等功能
Home-page: https://gitee.com/chinahehe/hehey-hcontainer
Author: 13564768842
Author-email: chinabluexfw@163.com
License: UNKNOWN
Platform: UNKNOWN
